{
  "data": [
   {
      "id": 1,
      "name": "阿房影視",
      "url": "http://api.hszbj.net/api.php/provide/vod/at/xml",
      "cate": "國產劇,10&&港台劇,11&&紀錄片,16&&日韓劇,12&&日劇,13&&歐美劇,14綜藝,1&&動漫,2&&動作片,3&&喜劇片,4&&愛情片,5&&科幻片,6&&恐怖片,7&&劇情片,8&&戰爭片,9&&&&懸疑片,15&&海外劇,17&&動畫片,18&&藍光資源,19&&其他劇,20&&古裝片,21&&青春片,22&&番劇,23&&站,24&&站電影,25&&站國產劇,26&&站動漫,27&&站紀錄片,28&&影視解說,29&&國創,30&&站港台劇,31&&站日韓劇,32&&站歐美劇,33&&動作片1,34&&喜劇片2,35&&愛情片3,36&&科幻片4,37&&恐怖片5,38&&劇情片6,39&&綜藝7,40&&動漫8,41&&動作片9,42&&喜劇片10,43&&愛情片11,44&&科幻片12,45&&恐怖片13,46&&劇情片14,47&&戰爭片15,48&&動漫16,49&&動作片17,50&&喜劇片18,51&&愛情片19,52&&科幻片20,53&&恐怖片21,54&&劇情片22,55&&戰爭片23,56&&國產劇24,57&&港台劇25,58&&日韓劇26,59&&歐美劇27,60&&懸疑片28,61&&紀錄片29,62&&海外劇30,63&&動畫片31,64&&藍光資源32,65&&其他劇33,66&&古裝片34,67&&青春片35,68&&番劇36,69&&站37,70&&站電影38,71&&站國產劇39,72&&站動漫40,73&&站紀錄片41,74&&影視解說42,75&&國創43,76&&站港台劇44,77&&站日韓劇45,78&&站歐美劇46,79&&綜藝47,80&&動漫48,81&&動作片49,82&&喜劇片50,83&&愛情片51,84&&科幻片52,85&&恐怖片53,86&&劇情片54,87&&戰爭片55,88",
      "click": true,
      "wePlus": {}
    },
    {
      "id": 1,
      "name": "天空雲",
      "url": "https://api.tiankongapi.com/api.php/provide/vod/at/xml/from/tkm3u8/",
      "cate": "國產劇,13&&動作片,6&&喜劇片,7&&愛情片,8&&科幻片,9&&恐怖片,10&&韓國劇,26&&美國劇,16&&日本劇,24&&大陸綜藝,33&&日韓綜藝,34&&國產動漫,28&&日本動漫,29&&歐美動漫,30",
      "click": true,
      "wePlus": {}
    },
    {
      "id": 1,
      "name": "八戒雲",
      "url": "http://cj.bajiecaiji.com/inc/bjm3u8.php",
      "cate": "國產劇,12&&動作片,5&&喜劇片,6&&愛情片,7&&科幻片,8&&恐怖片,9&&韓國劇,14&&美國劇,15&&日本劇,17&&內地綜藝,96日韓綜藝,97&&國產動漫,91&&日本動漫,92&&歐美動漫,93",
      "click": true,
      "wePlus": {}
    },
    {
      "id": 1,
      "name": "快雲",
      "url": "http://www.kuaibozy.com/api.php/provide/vod/from/kbm3u8/at/xml/",
      "cate": "國產劇,13&&動作片,6&&喜劇片,7&&愛情片,8&&科幻片,9&&恐怖片,10&&日韓劇,15&&美國劇,16&&綜藝,3&&動漫,4",
      "click": true,
      "wePlus": {}
    },
    {
      "id": 1,
      "name": "極品影視",
      "url": "https://www.jpysvip.net/api.php/provide/vod/at/xml/",
      "cate": "電影,1&&國產劇,13&&動作片,6&&港台劇,14&&連續劇,2&&綜藝,3&&動漫,4&&戰爭片,12&&喜劇片,7&&愛情片,8&&科幻片,9&&恐怖片,10&&劇情片,11&&日韓劇,15&&歐美劇,16",
      "click": true,
      "wePlus": {}
    },
    {
      "id": 1,
      "name": "88雲",
      "url": "http://www.88zyw.net/inc/m3u8.php",
      "cate": "國產劇,12&&動作片,5&&喜劇片,6&&愛情片,7&&科幻片,8&&恐怖片,9&&韓國劇,14&&美國劇,15綜藝,3&&國產動漫,22&&日本動漫,21&&歐美動漫,23",
      "click": true,
      "wePlus": {}
    }
  ]
}